toutiao.py
omnimd_toutiao_reader-0.1.4.dist-info/METADATA
omnimd_toutiao_reader-0.1.4.dist-info/WHEEL
omnimd_toutiao_reader-0.1.4.dist-info/entry_points.txt
omnimd_toutiao_reader-0.1.4.dist-info/RECORD
